webauth/__init__.py
webauth/admin.py
webauth/apps.py
webauth/decorators.py
webauth/mixins.py
webauth/models.py
webauth/tests.py
webauth/urls.py
webauth/views.py
webauth/migrations/0001_initial.py
webauth/migrations/__init__.py
webauth/static/webauth/bootstrap.bundle.min.js
webauth/static/webauth/bootstrap.bundle.min.js.map
webauth/static/webauth/bootstrap.min.css
webauth/static/webauth/bootstrap.min.css.map
webauth/templates/webauth/base.html
webauth/templates/webauth/webauthdevice_confirm_delete.html
webauth/templates/webauth/webauthdevice_list.html
webauth/templates/webauth/webauthdevice_verify.html
django_webauth-0.1.2.dist-info/LICENSE
django_webauth-0.1.2.dist-info/METADATA
django_webauth-0.1.2.dist-info/WHEEL
django_webauth-0.1.2.dist-info/top_level.txt
django_webauth-0.1.2.dist-info/RECORD
